polyplotter/__init__.py
polyplotter/polyplotter.py
polyplotter/version.py
polyplotter-0.3.2.dist-info/LICENSE
polyplotter-0.3.2.dist-info/METADATA
polyplotter-0.3.2.dist-info/WHEEL
polyplotter-0.3.2.dist-info/top_level.txt
polyplotter-0.3.2.dist-info/RECORD
